README.rst
setup.cfg
setup.py
webtest_selenium/__init__.py
webtest_selenium/sel.py
webtest_selenium.egg-info/PKG-INFO
webtest_selenium.egg-info/SOURCES.txt
webtest_selenium.egg-info/dependency_links.txt
webtest_selenium.egg-info/entry_points.txt
webtest_selenium.egg-info/not-zip-safe
webtest_selenium.egg-info/requires.txt
webtest_selenium.egg-info/top_level.txt