Metadata-Version: 1.0
Name: webtest-selenium
Version: 0.1
Summary: Selenium testing with WebTest
Home-page: http://github.com/gawel/webtest-selenium
Author: Gael Pasgrimaud
Author-email: gael@gawel.org
License: MIT
Keywords: selenium webtest wsgi
Platform: UNKNOWN
